SimSCSnTree/Beta_Splitting_Model.py
SimSCSnTree/CN.py
SimSCSnTree/Gen_Ref_Fa.py
SimSCSnTree/__init__.py
SimSCSnTree/__main__.py
SimSCSnTree/bin_groundtruth.py
SimSCSnTree/bin_groundtruth_woSegCopy.py
SimSCSnTree/calculate_lorenz.py
SimSCSnTree/estimate_beta_dist.py
SimSCSnTree/flip_counter.py
SimSCSnTree/gen_newick.py
SimSCSnTree/gen_newick_chr.py
SimSCSnTree/gen_readcount.py
SimSCSnTree/gen_tree.py
SimSCSnTree/gen_tree_overlappingCNA.py
SimSCSnTree/main.par.overlapping.py
SimSCSnTree/main.par.py
SimSCSnTree/metropolis_hasting.py
SimSCSnTree/read_tree.py
SimSCSnTree/sep_groundtruth.py
SimSCSnTree-0.0.9.dist-info/LICENSE
SimSCSnTree-0.0.9.dist-info/METADATA
SimSCSnTree-0.0.9.dist-info/WHEEL
SimSCSnTree-0.0.9.dist-info/top_level.txt
SimSCSnTree-0.0.9.dist-info/RECORD
