Metadata-Version: 2.1
Name: SimSCSnTree
Version: 0.0.9
Summary: Simulating single cell sequencing data
Home-page: https://github.com/compbiofan/SimSCSnTree
Author: Xian Fan Mallory
Author-email: xfan2@fsu.edu
License: UNKNOWN
Platform: UNKNOWN
Classifier: Programming Language :: Python :: 3
Classifier: License :: OSI Approved :: MIT License
Classifier: Operating System :: OS Independent
Requires-Python: >=3.6
License-File: LICENSE
Requires-Dist: numpy (>=1.18.0)
Requires-Dist: anytree
Requires-Dist: scipy (==1.5.0)
